MegafonAPI/BaseConsts.py
MegafonAPI/HttpAdapter.py
MegafonAPI/LK.py
MegafonAPI/State.py
MegafonAPI/VATS.py
MegafonAPI/__init__.py
MegafonAPI-0.0.45.dist-info/METADATA
MegafonAPI-0.0.45.dist-info/WHEEL
MegafonAPI-0.0.45.dist-info/top_level.txt
MegafonAPI-0.0.45.dist-info/RECORD
