Metadata-Version: 2.1
Name: MegafonAPI
Version: 0.0.45
Summary: Python API implementation to work with Megafon business services
Home-page: https://github.com/robotkarl/MegafonAPI
Author: Ilya Strukov
Author-email: ilya@strukov.net
License: UNKNOWN
Platform: UNKNOWN
Classifier: Programming Language :: Python :: 3
Classifier: License :: OSI Approved :: MIT License
Classifier: Operating System :: OS Independent
Requires-Python: >=3.6
Requires-Dist: certifi (==2020.6.20)
Requires-Dist: chardet (==3.0.4)
Requires-Dist: pyquery (==1.4.1)
Requires-Dist: pytz (==2020.1)
Requires-Dist: requests (==2.24.0)
Requires-Dist: urllib3 (==1.25.10)
Requires-Dist: cssselect (==1.1.0) ; python_version >= "2.7" and python_version not in "3.0, 3.1, 3.2, 3.3"
Requires-Dist: idna (==2.10) ; python_version >= "2.7" and python_version not in "3.0, 3.1, 3.2, 3.3"
Requires-Dist: lxml (==4.5.2) ; python_version >= "2.7" and python_version not in "3.0, 3.1, 3.2, 3.3, 3.4"
